{
  "name": "Hilda Mendoza",
  "age": 47,
  "address": {
    "street": "Wowzi Manor",
    "city": "Gudbiic",
    "state": "NM",
    "zip": "05826"
  },
  "contact": {
    "phone": "(272) 751-5637",
    "servicePhone": "800428812"
  },
  "birthday": "1983-11-15T21:23:28.094Z",
  "ip": "222.153.22.218",
  "foo": "bar",
  "profile": {
    "about": "Imi gomuho fal darnosde bil eci ikgeoto vuf livlu wihgira wikkebmu cabsa oppinec genu hozuf. Fiszowgus jaddislu inmakha bulbiwip bi egigi il dur cev bihsenboc fuw og kuj tolzo. Sarve sajiz zaze dire ogori teha bopzovir bit bizane haz weg ikaegamic. Lulmempa tujajor sikilvib sol buc demjen samezcow wuboh ate is fo senaza cozmesa rirtu ninaf kibemi pu. Wiwutepo ehuwo ziterju nosiiv ve fite opubodo gifi ihe fogizac fatliz sewhur gi zow hu udfunak jirrazta. Gupi isotsef ido idlale erala we te ariju obouti firle ikruz ebi enfer rifaza lo cuca dilane. Ce ziza geawi zammarizi pefroj fepgebi aw uk ze uf rahoz hasenisu wavuh ajifum pocriv pa puseele.",
    "bio": "Webutkuk fa fe zopo ci pukegihib leuge muku onu mikumog lojne apsi tigeci velkilpa hiwiciz pavmafil detcun. Ap wipifa lav pavuho vef ne to wuvzumuw pidepnaw we neetamo ci. Jozug du bawserva bakid pa pidag ehvermom refozi ko rehev ecolit vegive holuvma ufumo vabolam tosifina. Ij nem valrolput idu fot ol di jupubni diokata te uvukup zabfepat. Vigdu kurowloj pe mora awo nimim eka ujakugpi lujos jigcojos koenicu domamo daszudbe ihocal. Git calwovju giwnolaf liojani beh faj noz guhzis hadvud doffi kes tekog sekbilbel terbowo losfale waocidi ufeliral ti. Fottisen jup ga ehipaj bodbespi ugeji tejpi wimsotva gewih had hak nemni kebku novwe odco."
  },
  "apiKey": "d944bf23ad72c2fd1fc0b271825c609bf7e5d36ef509362bb2f541e731bf5b33",
  "currency": {
    "code": "QAR",
    "name": "Qatar Riyal"
  }
}