{
  "name": "Minerva Webster",
  "age": 26,
  "address": {
    "street": "Apizi Mill",
    "city": "Wecego",
    "state": "AZ",
    "zip": "02485"
  },
  "contact": {
    "phone": "(819) 696-6772",
    "servicePhone": "800579873"
  },
  "birthday": "1989-04-04T14:23:50.670Z",
  "ip": "29.193.255.217",
  "foo": "bar",
  "profile": {
    "about": "Gumpidigu vuj azaugufab su esa okurud nutima obbos wawuwnut jetav zuhjaf ko roul ti jibah. Azefa uwifuh cevepe fomkopur arahvez era jo fu lucuh votza ta zeg pukbef dufgo gure jutabwa rokcucnan wejev. Ekovkun bukibe omhucab wikrujhuv kam as kedaveawe nahun mubure no cesose bacjis. Sitho ohoago gal de fiikado bucu getla demgasib kapto oh aha befepzo. Vubo okjele da evegiw peho mi agozosov co tebelej kunu gah kamcikin apa.",
    "bio": "Henihuj nu nodulor kacol kefut humzuzto jopevfo asgac elive pa ku babodaj urale iwfe. Tapmoeb loz agkeguc te ovo meg om dahli ogza hi tu duhu ecirokiwi deiz ructuefa laozlow. Fear hajmufek igwi owlewih omaburuf jolse ehasoswez ca cozip fatgonhew ik sefebi. Aludwih liwuc rohaz iztogo nonvimol su ifu rogi so hiti othopvij efadu hoctacke pik geg suifu. Nirodzih hatidiva pa amieb jinhuaru bor unba rozof sumsotow ez jas momruvap elowu."
  },
  "apiKey": "f4638bffc67ab569aaea112ef30ace8d2c8b09ffbf4f71c44082f584e46f5952",
  "currency": {
    "code": "RON",
    "name": "Romania New Leu"
  }
}